LICENSE
MANIFEST.in
README.rst
conftest.py
setup.py
utvsapitoken/__init__.py
utvsapitoken/client.py
utvsapitoken/exceptions.py
utvsapitoken/fakeserver.py
utvsapitoken.egg-info/PKG-INFO
utvsapitoken.egg-info/SOURCES.txt
utvsapitoken.egg-info/dependency_links.txt
utvsapitoken.egg-info/requires.txt
utvsapitoken.egg-info/top_level.txt
utvsapitoken/tests/test_client.py