Metadata-Version: 1.1
Name: utvsapitoken
Version: 0.0.2
Summary: OAuth2 token validation for UTVS API
Home-page: https://github.com/hroncok/utvsapitoken
Author: Miro Hrončok
Author-email: miro@hroncok.cz
License: MIT
Keywords: oauth2
Platform: UNKNOWN
Classifier: Development Status :: 3 - Alpha
Classifier: Intended Audience :: Developers
Classifier: License :: OSI Approved :: MIT License
Classifier: Operating System :: POSIX :: Linux
Classifier: Programming Language :: Python
Classifier: Programming Language :: Python :: 3 :: Only
